[{"start":"6.68","dur":"2.659","text":"maar"},{"start":"23.4","dur":"8.53","text":"kijk over stoffen af en toe schap"},{"start":"30.19","dur":"5.49","text":"krijgt en als je binnenkomt jij nog"},{"start":"31.93","dur":"5.97","text":"nooit goed nou nou oké goed dus nu oké"},{"start":"35.68","dur":"5.79","text":"dit is rap news widow creme benen"},{"start":"37.9","dur":"8.85","text":"ja da's grappig is ik echt graag kijk"},{"start":"41.47","dur":"6.75","text":"naar toch is het heel lang kapot nou ja"},{"start":"46.75","dur":"3","text":"hulk ook eens een keer iets leuks zijden"},{"start":"48.22","dur":"2.85","text":"bekleed met je grote dikke poten op"},{"start":"49.75","dur":"4.73","text":"staan"},{"start":"51.07","dur":"3.41","text":"nou dit is dus we bestnr"},{"start":"54.64","dur":"8.58","text":"ja nou niks houdt hoe gaat met jou"},{"start":"58.15","dur":"8.81","text":"formido zeer heb gedaan heb ik mooi"},{"start":"63.22","dur":"3.74","text":"bloemen ja dit leuk"},{"start":"67.63","dur":"3.9","text":"nou ik zou zeggen eet smakelijk probeer"},{"start":"70.72","dur":"6.57","text":"het"},{"start":"71.53","dur":"7.89","text":"ja ik pak bleek uurtjes nu ja hoe noem"},{"start":"77.29","dur":"5.219","text":"jij slaat ik heb gewoon een keertje"},{"start":"79.42","dur":"5.1","text":"anders om de boel een beetje van ander"},{"start":"82.509","dur":"4.64","text":"ik hoop dat je jouw dat een beetje een"},{"start":"84.52","dur":"2.629","text":"lol mee te doen"},{"start":"88.06","dur":"4.46","text":"mijn god die potten leuk om hun invloed"},{"start":"90.28","dur":"5.28","text":"die gierig bulk"},{"start":"92.52","dur":"5.29","text":"nou heb ik het is ook geen zin meer in"},{"start":"95.56","dur":"4.14","text":"schroom eten met stokjes ja die zitten"},{"start":"97.81","dur":"11.309","text":"doe je in londen met een bakje beeld"},{"start":"99.7","dur":"13.14","text":"ja oké dat is die jou ook hier nu ik"},{"start":"109.119","dur":"5.761","text":"lijk wel een paard hebt ook rechts nooit"},{"start":"112.84","dur":"6.529","text":"in het nieuws en dat is normaal voor job"},{"start":"114.88","dur":"4.489","text":"nu wil je in moet ik nou weer"},{"start":"119.8","dur":"10","text":"ja de ge mannetje dramatische kans mis"},{"start":"127.27","dur":"6.79","text":"keer ik ben nieuwe"},{"start":"129.8","dur":"8.19","text":"nieuwe sfeer ja de sfeer van jou al"},{"start":"134.06","dur":"8.45","text":"jaren hmm er gewoon wie ik ben maar de"},{"start":"137.99","dur":"4.52","text":"dit merapi nou ja zit met uur"},{"start":"147.83","dur":"4.23","text":"wat is dit nou voor attitude die je"},{"start":"149.87","dur":"4.29","text":"maakt"},{"start":"152.06","dur":"3.69","text":"creativiteit het kan ook nog wel eens"},{"start":"154.16","dur":"2.25","text":"een keertje een kans krijgen of niet"},{"start":"155.75","dur":"4.62","text":"soms"},{"start":"156.41","dur":"5.88","text":"ja ik neem het sportief op dat jij zo'n"},{"start":"160.37","dur":"3.9","text":"om binnenkort tot neem ik sportief op"},{"start":"162.29","dur":"3.51","text":"dat mag je verder geen woorden olie vuil"},{"start":"164.27","dur":"5.12","text":"en wat doe jij"},{"start":"165.8","dur":"5.93","text":"nee check de hele zaak te verknallen"},{"start":"169.39","dur":"6.79","text":"zoals gewoonlijk"},{"start":"171.73","dur":"6.52","text":"ja nou je bent wel op sino-japanse te"},{"start":"176.18","dur":"3.54","text":"veel gezien maar ga erin gedrukt het je"},{"start":"178.25","dur":"5.25","text":"panopsis"},{"start":"179.72","dur":"8.519","text":"dat je dat wel mag ik vroeg ik heel even"},{"start":"183.5","dur":"7.11","text":"in toen het werd een zich met"},{"start":"188.239","dur":"4.711","text":"voor deïst in zit ik genoot wat maakt"},{"start":"190.61","dur":"6.93","text":"het ik bescherm"},{"start":"192.95","dur":"8.37","text":"blessures hier en deze ellende over help"},{"start":"197.54","dur":"5.97","text":"zei heb ik weet wel hoe het komt"},{"start":"201.32","dur":"4.8","text":"ze hebben altijd een handje gehad van"},{"start":"203.51","dur":"6.6","text":"zich te laten beinvloeden"},{"start":"206.12","dur":"8.25","text":"zeg ik nou 5 vrienden guijt die het ook"},{"start":"210.11","dur":"8.25","text":"daadwerkelijk met hd de die ze altijd ja"},{"start":"214.37","dur":"6.78","text":"door de eigen respons peace in de hoofd"},{"start":"218.36","dur":"5.67","text":"zicht geuit gematigdheid zich heb laten"},{"start":"221.15","dur":"3.63","text":"beïnvloeden door gors eden was een"},{"start":"224.03","dur":"3.81","text":"spanjaard"},{"start":"224.78","dur":"5.79","text":"k manier hebben ze een turkse jongen nou"},{"start":"227.84","dur":"4.83","text":"noem het hele liedje maar op chip zich"},{"start":"230.57","dur":"3.54","text":"eigen nooit zelf een indentiteit kunnen"},{"start":"232.67","dur":"2.91","text":"schaffen"},{"start":"234.11","dur":"3.61","text":"en dit vind ik heel rap om dit nou weer"},{"start":"235.58","dur":"3.97","text":"te zien p"},{"start":"237.72","dur":"6.41","text":"je hebt net goed wordt er gespeeld heb"},{"start":"239.55","dur":"4.58","text":"het er nu mee heeft genomen"},{"start":"245.64","dur":"10.26","text":"dan moet jij nou"},{"start":"249.9","dur":"12.69","text":"donderde hol en ja ja ja nee het is"},{"start":"255.9","dur":"9.02","text":"natuurlijk geen stip ik met profilease"},{"start":"262.59","dur":"2.33","text":"doet"},{"start":"265.11","dur":"5.73","text":"schip van de eigen eigenlijk helemaal"},{"start":"268.86","dur":"4.02","text":"geen grip meer in het zien naam in deze"},{"start":"270.84","dur":"3.99","text":"situatie"},{"start":"272.88","dur":"4.71","text":"dit ze zich dan toch teveel hebt laten"},{"start":"274.83","dur":"7.08","text":"manipuleren door de hele wereld onder"},{"start":"277.59","dur":"5.76","text":"heen zodat ze zelf geen kant meer op kan"},{"start":"281.91","dur":"4.02","text":"en het heet waarschijnlijk te maken met"},{"start":"283.35","dur":"6.66","text":"invloed van de vader"},{"start":"285.93","dur":"6.48","text":"want ja ik vind het niet meer josee uit"},{"start":"290.01","dur":"11.99","text":"ijsselmonde hier kunnen we meppen en"},{"start":"292.41","dur":"9.59","text":"nieuw het gebeurt heb liever schijf"},{"start":"302.46","dur":"6","text":"heb ik te maken met je vader"},{"start":"305.46","dur":"5.19","text":"dat je niet meer weet wie je bent"},{"start":"308.46","dur":"6.69","text":"dat je al zoveel dingen nodig hebt om"},{"start":"310.65","dur":"13.35","text":"hier zelf een identiteit te geven liever"},{"start":"315.15","dur":"12.23","text":"schijt rivier tot een leuk dat je pols"},{"start":"324","dur":"3.38","text":"spul zeg dit hulpprogramma"},{"start":"328.5","dur":"4.5","text":"briefje hartendiefje people het oproep"},{"start":"332.4","dur":"2.97","text":"op"},{"start":"333","dur":"4.94","text":"mag ik even aan je poelen be put en tv"},{"start":"335.37","dur":"10.1","text":"maar glamour"},{"start":"337.94","dur":"11.07","text":"die staat hier te lachen toen ja"},{"start":"345.47","dur":"3.54","text":"en dit kunnen we"},{"start":"349.03","dur":"5.58","text":"met die q mijn moet doen dit weet ik"},{"start":"351.789","dur":"4.141","text":"vooralsnog niet misschien wel modem"},{"start":"354.61","dur":"4.829","text":"beetje uitgebuite"},{"start":"355.93","dur":"5.25","text":"schat ik ben maar goed dit is allemaal"},{"start":"359.439","dur":"4.801","text":"weer goed gekomen"},{"start":"361.18","dur":"6.18","text":"natuurlijk is josee creatief"},{"start":"364.24","dur":"4.829","text":"natuurlijk elk mens elk mens laat zich"},{"start":"367.36","dur":"4.23","text":"beïnvloeden"},{"start":"369.069","dur":"3.541","text":"elk mens pik dingen op die zich om zich"},{"start":"371.59","dur":"3.99","text":"heen afspelen"},{"start":"372.61","dur":"5.609","text":"natuurlijk ga je je pense tafeltje maken"},{"start":"375.58","dur":"6.6","text":"als je hem dan ziet ie mooi judo wakker"},{"start":"378.219","dur":"6.061","text":"natuurlijk in dit vinden vader heb ze"},{"start":"382.18","dur":"4.26","text":"gelukkig niet gehoord van de toevoegen"},{"start":"384.28","dur":"4.65","text":"deur dicht was het komt allemaal weer"},{"start":"386.44","dur":"7.129","text":"goed want er is maar één taal die"},{"start":"388.93","dur":"4.639","text":"overleven en dit is de lichamen straf"}]