[{"start":"0","dur":"6.05","text":"[Muziek]"},{"start":"4.46","dur":"3.27","text":"heeft uw man"},{"start":"6.05","dur":"4.259","text":"exclusief en alleen bij de vpro te"},{"start":"7.73","dur":"4.26","text":"bestellen en video een plakjes gevecht"},{"start":"10.309","dur":"4.41","text":"met een uitgelezen selectie uit de"},{"start":"11.99","dur":"5.64","text":"seizoenen in 90 tot 94"},{"start":"14.719","dur":"4.141","text":"die mag je niet missen en de cd jiskefet"},{"start":"17.63","dur":"2.94","text":"volume een"},{"start":"18.86","dur":"3.63","text":"met een ongekende hoeveelheid nooit"},{"start":"20.57","dur":"4.35","text":"eerder uitgebracht materiaal"},{"start":"22.49","dur":"4.26","text":"een must voor de ware liefhebber eerste"},{"start":"24.92","dur":"4.25","text":"verder laat zich kopen zolang de"},{"start":"26.75","dur":"2.42","text":"voorraad strekt"},{"start":"29.34","dur":"5.599","text":"[Muziek]"}]