[{"start":"13.02","dur":"3.39","text":"kijk goed"},{"start":"28.31","dur":"3","text":"inloggen"},{"start":"33.239","dur":"7.89","text":"ja"},{"start":"35.8","dur":"5.329","text":"jij moet hem en jou"},{"start":"44.44","dur":"10.79","text":"hey hoe is hier laat zitten"},{"start":"55.36","dur":"5.479","text":"ja kom maar over de drempel tjee"},{"start":"58.48","dur":"2.359","text":"ze meneer"},{"start":"67.14","dur":"5.36","text":"doe mij hoef je thuis bent wij zijn hele"},{"start":"69.78","dur":"2.72","text":"normale mensen"},{"start":"72.84","dur":"6.38","text":"wij vroegen onze lena en"},{"start":"75.69","dur":"8.16","text":"of jij enig fatsoen ier sodemieter het"},{"start":"79.22","dur":"10.66","text":"is niet zo leuk en ook niet voor andere"},{"start":"83.85","dur":"7.41","text":"mensen onder jou te moeten kijken we"},{"start":"89.88","dur":"3.21","text":"zijn allemaal mensen die proberen er"},{"start":"91.26","dur":"3.66","text":"iets van te maken"},{"start":"93.09","dur":"5.19","text":"maar ik heb de godverdomme begaan nog"},{"start":"94.92","dur":"5.22","text":"nooit helemaal niet vaak tot zien heel"},{"start":"98.28","dur":"3.96","text":"op die marjo zijn potten mayonaise met"},{"start":"100.14","dur":"4.7","text":"slasaus benen of er niks aan de hand is"},{"start":"102.24","dur":"2.6","text":"over de camping"},{"start":"104.88","dur":"6.63","text":"ik snap dit niet dat jij de niet iets"},{"start":"107.82","dur":"6.299","text":"aan kunt doen hij was vroeg helemaal"},{"start":"111.51","dur":"4.71","text":"niks hij heeft er ook al gewerkt"},{"start":"114.119","dur":"4.831","text":"we willen er allemaal leuk uit zien kijk"},{"start":"116.22","dur":"4.59","text":"dat lichaam gaat wil en ik kan niet in"},{"start":"118.95","dur":"7.23","text":"je hoofd kijken"},{"start":"120.81","dur":"7.47","text":"maar die kunnen wel op kijken het is"},{"start":"126.18","dur":"6.089","text":"godverdomme of ik zie te kijken naar een"},{"start":"128.28","dur":"8.929","text":"mooi onding en tegenwoordig is er wel"},{"start":"132.269","dur":"4.94","text":"spul je de heel wat aan kan doen om dit"},{"start":"139.55","dur":"5.56","text":"kan best hoeft de bladen maar open te"},{"start":"142.65","dur":"4.95","text":"slaan en je ziet op wijs en collins en"},{"start":"145.11","dur":"4.95","text":"collins schedel in een man wat is hier"},{"start":"147.6","dur":"4.74","text":"weer een hele hoek er in de doos"},{"start":"150.06","dur":"3.929","text":"nee mannen die verdomd het die kinderen"},{"start":"152.34","dur":"3.63","text":"van mij die wordt dus naars gillend"},{"start":"153.989","dur":"4.021","text":"wakker en hier hebben ze het over een"},{"start":"155.97","dur":"3.78","text":"man met een blauw shirtje is zou mij"},{"start":"158.01","dur":"3.12","text":"niet verbazen die kinderen dus als de"},{"start":"159.75","dur":"3.51","text":"dood zijn voor jou"},{"start":"161.13","dur":"6.06","text":"en dit is niet leuk voor ons en dit is"},{"start":"163.26","dur":"7.1","text":"helemaal niet leuk hoor die camping"},{"start":"167.19","dur":"3.17","text":"douchen wordt gehouden en toe"},{"start":"172.46","dur":"8.28","text":"en jij weet verdomd goed wat ik het"},{"start":"176.73","dur":"8.82","text":"alweer ik weet niet heb jij een vriendin"},{"start":"180.74","dur":"6.85","text":"lijkt me van niet hoe blij mee met deze"},{"start":"185.55","dur":"3.75","text":"zij op die doorschuift"},{"start":"187.59","dur":"3.18","text":"lijkt mij het geen likken gesierd om die"},{"start":"189.3","dur":"4.44","text":"afgetrapte heidebrand"},{"start":"190.77","dur":"5.82","text":"te moeten afhouden misschien heb jij de"},{"start":"193.74","dur":"9.08","text":"ziekte van hedel"},{"start":"196.59","dur":"6.23","text":"van hedel de ziekten ziekten beneden"},{"start":"204.8","dur":"3.59","text":"smeer haar op je lord en op je schedel"},{"start":"212.65","dur":"4.419","text":"hierdoor zullen ging en hij is anders"},{"start":"215.33","dur":"2.4","text":"ook persoonlijk hoor eens ik niet doe"},{"start":"217.069","dur":"5.781","text":"het niet"},{"start":"217.73","dur":"5.12","text":"hi stand staan"},{"start":"223.16","dur":"17.609","text":"atleon kijken doe niets door de"},{"start":"227.36","dur":"20.52","text":"worden door en door door toch niet nou"},{"start":"240.769","dur":"11.521","text":"die bij jouw het gaat om jou niet lachen"},{"start":"247.88","dur":"8.4","text":"maar goed is al acht al die nog een hele"},{"start":"252.29","dur":"6.949","text":"camping op jou gewoon lachen naar wel"},{"start":"256.28","dur":"2.959","text":"bewijs is niet"},{"start":"262.88","dur":"10.32","text":"leg mijn huis uit die de hopi's met die"},{"start":"267.87","dur":"8.4","text":"komt van jou weet jij het mij die ik het"},{"start":"273.2","dur":"5.85","text":"maar kunnen wel wat aan doen"},{"start":"276.27","dur":"2.78","text":"een dag hadden toe"},{"start":"283.87","dur":"2.87","text":"ja"},{"start":"296.25","dur":"3","text":"ja"},{"start":"312.849","dur":"15.24","text":"snel keer goddelijke définit werken ja"},{"start":"322.599","dur":"10.97","text":"nou weer bij hem ziet een middel van de"},{"start":"328.089","dur":"5.48","text":"rug over hadden week goed zo"},{"start":"347.96","dur":"6.87","text":"ook andersom biscuit mensen heel lang"},{"start":"352.35","dur":"2.48","text":"niet meer zo"},{"start":"356.48","dur":"10.36","text":"nee doe dat niet er bij"},{"start":"362.43","dur":"6.47","text":"hier commons rhedens reden"},{"start":"366.84","dur":"6.33","text":"sietse"},{"start":"368.9","dur":"8.97","text":"donder dank u wel heerlijk"},{"start":"373.17","dur":"4.7","text":"kijkt u eens kijken of shoppen"},{"start":"381.21","dur":"7.92","text":"wat in een een stukje shift jaar"},{"start":"385.03","dur":"4.1","text":"had ik een tip geeft ja"}]