[{"start":"0.69","dur":"15.949","text":"[Muziek]"},{"start":"11.929","dur":"4.71","text":"maak je wel hij zijn het ellebogen"},{"start":"17.01","dur":"2.359","text":"of hier"},{"start":"19.47","dur":"5.2","text":"ja met mijn bepaald moment al besloten"},{"start":"22.62","dur":"4.36","text":"mijn zoon die moest het huis uit"},{"start":"24.67","dur":"3.24","text":"militaire dienst"},{"start":"26.98","dur":"4.38","text":"toen dachten wij met de hele"},{"start":"27.91","dur":"5.22","text":"problematiek die er natuurlijk is het"},{"start":"31.36","dur":"3","text":"zoeken naar woonruimte waard zijn dan"},{"start":"33.13","dur":"2.73","text":"hebben waar zij het extra moeilijk mee"},{"start":"34.36","dur":"4.19","text":"want zonder verblijfsvergunning zonder"},{"start":"35.86","dur":"4.92","text":"werk voor honingbijen helemaal nergens"},{"start":"38.55","dur":"6.22","text":"dat wij daar een wat we hebben toch dat"},{"start":"40.78","dur":"7.08","text":"kamertje nog vrij staan dus waarom"},{"start":"44.77","dur":"6.27","text":"zouden we niet eens een loop neem het is"},{"start":"47.86","dur":"5.19","text":"natuurlijk ook zou wetten en waarderen"},{"start":"51.04","dur":"5.58","text":"12 kinderen in huis dus het laatst is"},{"start":"53.05","dur":"4.5","text":"dus ja ondanks het huis uitgegaan van"},{"start":"56.62","dur":"4.71","text":"jij al zei"},{"start":"57.55","dur":"10.26","text":"en ja je zit er getoond blik met een"},{"start":"61.33","dur":"8.37","text":"en verdeelt europa en ja heb je de 12 in"},{"start":"67.81","dur":"3.18","text":"huis gehad om dus altijd ja al die"},{"start":"69.7","dur":"4.95","text":"kinderen van ons en tuurlijk met liefde"},{"start":"70.99","dur":"4.919","text":"opgevoed en evia als ze thuis bij de is"},{"start":"74.65","dur":"3.29","text":"onze liefde kunnen overdragen naar"},{"start":"75.909","dur":"6.271","text":"andere mensen waarom zou hij niet doen"},{"start":"77.94","dur":"7.27","text":"en dat is wat ik zei dat heel europa het"},{"start":"82.18","dur":"4.38","text":"is een een grotere gekrakeel wij mensen"},{"start":"85.21","dur":"2.07","text":"vinden elkaar niet meer leuk die al"},{"start":"86.56","dur":"2.88","text":"jarenlang"},{"start":"87.28","dur":"3.81","text":"naast elkaar hebben gewoon de het is ook"},{"start":"89.44","dur":"4.08","text":"om een sociaal actief hebben wat wel en"},{"start":"91.09","dur":"4.5","text":"niet kan en wat wel en niet aardig is ik"},{"start":"93.52","dur":"3.75","text":"bedoel het toch en eigenlijk kun je hoge"},{"start":"95.59","dur":"4.74","text":"hoge hek zien dat is toch ook eigenlijk"},{"start":"97.27","dur":"5.16","text":"een groot huis en dan moeten we toch"},{"start":"100.33","dur":"3.72","text":"allemaal samen leven"},{"start":"102.43","dur":"2.7","text":"de hele wereld is wat het bedrijf in"},{"start":"104.05","dur":"2.64","text":"zijn gesloten huis hebben wij hebben het"},{"start":"105.13","dur":"3.33","text":"hier met zijn 12 nou dat natuurlijk heb"},{"start":"106.69","dur":"3.3","text":"je wel ruzies zijn gedonder ik wat"},{"start":"108.46","dur":"3.57","text":"uitlaat hebben gaan mensen als er om er"},{"start":"109.99","dur":"3.84","text":"grote gezellige familie ja dat was hier"},{"start":"112.03","dur":"3.27","text":"in huis halen van juist een jaar de ene"},{"start":"113.83","dur":"3.09","text":"die stond de ballen de aan de laten we"},{"start":"115.3","dur":"3.06","text":"gewoon naar onszelf loungeset is het"},{"start":"116.92","dur":"4.35","text":"denk ik dat het heel anders dan een"},{"start":"118.36","dur":"5.37","text":"slaaf linkedin in je spel volledig in"},{"start":"121.27","dur":"4.08","text":"roze waar je hoort of van de ander wat"},{"start":"123.73","dur":"3.71","text":"elkaar wat wat je dan zijn er sinds je"},{"start":"125.35","dur":"3.53","text":"weet niet luistert of jou eens naar"},{"start":"127.44","dur":"3.56","text":"helemaal en dat hebben wij als ik"},{"start":"128.88","dur":"4.23","text":"tachtig bij de machine batterij"},{"start":"131","dur":"4.69","text":"gelijkmatiger in een zijn dat goed op"},{"start":"133.11","dur":"4.14","text":"gang doe ik altijd gezellig hier zit en"},{"start":"135.69","dur":"4.17","text":"wat anders maar missen twee en tafel dat"},{"start":"137.25","dur":"4.23","text":"je dan mixen en voor mijn paris missen"},{"start":"139.86","dur":"3.87","text":"12 van tafels in"},{"start":"141.48","dur":"4.71","text":"toch hartstikke gezellig het is toch ook"},{"start":"143.73","dur":"4.05","text":"een stukje stelt dat ik een groot ja dat"},{"start":"146.19","dur":"3.96","text":"wordt dan toch wat achter je rug merk je"},{"start":"147.78","dur":"3.84","text":"wel gelovigen kwettert"},{"start":"150.15","dur":"2.7","text":"maar dat verstond dan wel gaan we ze"},{"start":"151.62","dur":"4.62","text":"merken wat een verdomd haar sieraden"},{"start":"152.85","dur":"5","text":"hemelen toch eigenlijk is dus ja je kan"},{"start":"156.24","dur":"5.13","text":"toch wel ik wil zeggen dat het een"},{"start":"157.85","dur":"4.66","text":"gentleman sh had de deur voor jou was"},{"start":"161.37","dur":"3.57","text":"met mijn oudste zoon die dan in een"},{"start":"162.51","dur":"3.96","text":"militair links is als je dan zelf te"},{"start":"164.94","dur":"3.06","text":"sparen douche kwam de lage toch al gauw"},{"start":"166.47","dur":"3.21","text":"zo'n slap op je haar met zo'n nog iets"},{"start":"168","dur":"2.37","text":"anders kleber eft op texel 8 aan een"},{"start":"169.68","dur":"2.67","text":"tafel pretje"},{"start":"170.37","dur":"3.54","text":"[Muziek]"},{"start":"172.35","dur":"5.01","text":"maar deze jongen die ruimte alles heel"},{"start":"173.91","dur":"4.5","text":"erg euro ook heel erg op zijn kleding is"},{"start":"177.36","dur":"2.61","text":"stil"},{"start":"178.41","dur":"3.72","text":"het is wat dat betreft hij slaapt hij"},{"start":"179.97","dur":"7.04","text":"slaapt dat het op zijn broek er om de"},{"start":"182.13","dur":"6.9","text":"studenten en het is natuurlijk ook ja"},{"start":"187.01","dur":"3.82","text":"natuurlijk wat een vrouw je bent een"},{"start":"189.03","dur":"5.709","text":"vrouw wij zijn vrouw een beetje op"},{"start":"190.83","dur":"6.879","text":"leeftijd maar ja"},{"start":"194.739","dur":"4.47","text":"hij heet u graag bij kaarslicht dus zie"},{"start":"197.709","dur":"4.021","text":"je zo the flick willen vliegen en"},{"start":"199.209","dur":"4.951","text":"allemaal in een yazid ook iets ondeugend"},{"start":"201.73","dur":"5.1","text":"cindy alle niet uit mijn en het op"},{"start":"204.16","dur":"5.49","text":"ingaan maar je vrouw zijn wordt"},{"start":"206.83","dur":"3.84","text":"natuurlijk ook een beetje weet je op die"},{"start":"209.65","dur":"2.339","text":"manier op die manier een beetje"},{"start":"210.67","dur":"3.45","text":"geactiveerd"},{"start":"211.989","dur":"3.81","text":"reis omdat het ook zo'n gentleman is het"},{"start":"214.12","dur":"3.3","text":"is tegelijkertijd iets met een vrouw op"},{"start":"215.799","dur":"4.351","text":"verlangt dat het gewone"},{"start":"217.42","dur":"6.36","text":"ook wester heet zijn gedonder is snack"},{"start":"220.15","dur":"5.91","text":"zo'n plakaat aan zijn ach ja misschien"},{"start":"223.78","dur":"7.19","text":"is dat wel leuk als mijn pakt u zou de"},{"start":"226.06","dur":"4.91","text":"kaarten spelletje wist"},{"start":"231.37","dur":"14.26","text":"[Muziek]"},{"start":"242.86","dur":"5.05","text":"we hebben dus nu met de sociale dienst"},{"start":"245.63","dur":"3.72","text":"afgesproken dat hij dus dat we daar wat"},{"start":"247.91","dur":"3.54","text":"geld voor krijgen dat jouw product kunt"},{"start":"249.35","dur":"4.02","text":"bellen naar zijn familie en hij wil je"},{"start":"251.45","dur":"4.68","text":"dat gezellig want dat kunnen ze goed het"},{"start":"253.37","dur":"4.589","text":"gezellige kwetteren de boom"},{"start":"256.13","dur":"3.81","text":"we gaan later zijn we dan toch af en toe"},{"start":"257.959","dur":"3.241","text":"wel eens jaloers op de wetten zijn hier"},{"start":"259.94","dur":"3.96","text":"op een man je hulp aan mij"},{"start":"261.2","dur":"5.37","text":"dus rekening we wel een soort tijden met"},{"start":"263.9","dur":"4.08","text":"de map moeten spreken over we bellen dat"},{"start":"266.57","dur":"4.069","text":"het na tienen niet meer is want je doet"},{"start":"267.98","dur":"5.82","text":"een bepaald met dus ook geen hoge minder"},{"start":"270.639","dur":"4.541","text":"want is nogal ja als week ik wilde"},{"start":"273.8","dur":"4.8","text":"verder helemaal geen waardeoordeel"},{"start":"275.18","dur":"4.77","text":"aannam vast klinken maar het is toch op"},{"start":"278.6","dur":"3.45","text":"zeer de wordt officieel"},{"start":"279.95","dur":"3.84","text":"luide zeg maar één ding in het donker"},{"start":"282.05","dur":"3.74","text":"telefoon meer"},{"start":"283.79","dur":"3.98","text":"dat is gewoon zeg maar louisa"},{"start":"285.79","dur":"4.83","text":"en dat vinden wij het punt om zijn zijn"},{"start":"287.77","dur":"4.38","text":"stem weer hun cultuur is net zoiets als"},{"start":"290.62","dur":"4.01","text":"je tegen een fransman zou haar zeggen"},{"start":"292.15","dur":"2.48","text":"van"},{"start":"294.64","dur":"3.72","text":"werd de rode wijn maar weer in de kast"},{"start":"296.2","dur":"8.06","text":"saus van weer genoeg francois en dat"},{"start":"298.36","dur":"9.65","text":"doen wij gewoon niet ja maar het is wel"},{"start":"304.26","dur":"3.75","text":"het is wel harten"},{"start":"309.99","dur":"4.98","text":"horen"},{"start":"310.47","dur":"4.5","text":"[Muziek]"}]